carto_auth/__init__.py
carto_auth/_version.py
carto_auth/auth.py
carto_auth/errors.py
carto_auth/pkce.py
carto_auth/utils.py
carto_auth-0.2.0.dist-info/LICENSE
carto_auth-0.2.0.dist-info/METADATA
carto_auth-0.2.0.dist-info/WHEEL
carto_auth-0.2.0.dist-info/top_level.txt
carto_auth-0.2.0.dist-info/RECORD
