Metadata-Version: 2.1
Name: carto-auth
Version: 0.2.0
Summary: Python library to authenticate with CARTO
Home-page: https://github.com/cartodb/carto-auth
Author: CARTO
Author-email: jarroyo@carto.com
License: BSD 3-Clause
Keywords: carto,auth,oauth,carto-dw,bigquery
Platform: UNKNOWN
Classifier: Development Status :: 5 - Production/Stable
Classifier: Intended Audience :: Developers
Classifier: License :: OSI Approved :: BSD License
Classifier: Natural Language :: English
Classifier: Programming Language :: Python :: 3
Classifier: Programming Language :: Python :: 3.7
Classifier: Programming Language :: Python :: 3.8
Classifier: Programming Language :: Python :: 3.9
Requires-Python: >=3.7
Requires-Dist: pyyaml
Requires-Dist: requests
Provides-Extra: carto-dw
Requires-Dist: google-auth ; extra == 'carto-dw'
Requires-Dist: google-cloud-bigquery (>=2.34.4) ; extra == 'carto-dw'
